.flake8
.pylintrc
LICENSE
MANIFEST.in
README.md
pyproject.toml
tox.ini
Webware_for_Python.egg-info/PKG-INFO
Webware_for_Python.egg-info/SOURCES.txt
Webware_for_Python.egg-info/dependency_links.txt
Webware_for_Python.egg-info/entry_points.txt
Webware_for_Python.egg-info/requires.txt
Webware_for_Python.egg-info/top_level.txt
bin/editfile.bat
bin/editfile.py
docs/Makefile
docs/appdev.rst
docs/changes.rst
docs/conf.py
docs/config.rst
docs/copyright.rst
docs/deploy.rst
docs/index.rst
docs/install.rst
docs/make.bat
docs/migrate.rst
docs/miscutils.rst
docs/overview.rst
docs/plugins.rst
docs/psp.rst
docs/quickstart.rst
docs/requirements.txt
docs/style.rst
docs/taskkit.rst
docs/testing.rst
docs/tutorial.rst
docs/userkit.rst
docs/webutils.rst
docs/css/custom.css
docs/css/logo.png
docs/ref/index.rst
docs/ref/core/application.rst
docs/ref/core/configurableforserversidepath.rst
docs/ref/core/cookie.rst
docs/ref/core/exceptionhandler.rst
docs/ref/core/httpcontent.rst
docs/ref/core/httpexceptions.rst
docs/ref/core/httprequest.rst
docs/ref/core/httpresponse.rst
docs/ref/core/httpservlet.rst
docs/ref/core/importmanager.rst
docs/ref/core/index.rst
docs/ref/core/jsonrpcservlet.rst
docs/ref/core/page.rst
docs/ref/core/picklerpcservlet.rst
docs/ref/core/plugin.rst
docs/ref/core/properties.rst
docs/ref/core/request.rst
docs/ref/core/response.rst
docs/ref/core/rpcservlet.rst
docs/ref/core/servlet.rst
docs/ref/core/servletfactory.rst
docs/ref/core/session.rst
docs/ref/core/sessiondynamicstore.rst
docs/ref/core/sessionfilestore.rst
docs/ref/core/sessionmemcachedstore.rst
docs/ref/core/sessionmemorystore.rst
docs/ref/core/sessionredisstore.rst
docs/ref/core/sessionshelvestore.rst
docs/ref/core/sessionstore.rst
docs/ref/core/sidebarpage.rst
docs/ref/core/transaction.rst
docs/ref/core/unknownfiletypeservlet.rst
docs/ref/core/urlparser.rst
docs/ref/core/wsgistreamout.rst
docs/ref/core/xmlrpcservlet.rst
docs/ref/miscutils/configurable.rst
docs/ref/miscutils/csvjoiner.rst
docs/ref/miscutils/csvparser.rst
docs/ref/miscutils/datatable.rst
docs/ref/miscutils/dateinterval.rst
docs/ref/miscutils/dateparser.rst
docs/ref/miscutils/dbpool.rst
docs/ref/miscutils/dictforargs.rst
docs/ref/miscutils/error.rst
docs/ref/miscutils/funcs.rst
